[{"line":1,"elements":[{"start_timestamp":"2023-02-01T14:02:00.356Z","before":[{"result":{"duration":1995500,"status":"passed"},"match":{"location":"com.automation.steps.Hooks.setUp()"}}],"line":4,"name":"Verify user can remove item from cart","description":"","id":"to-verify-cart-page-functionalities;verify-user-can-remove-item-from-cart","after":[{"result":{"status":"passed"},"match":{"location":"com.automation.steps.Hooks.cleanUp()"}}],"type":"scenario","keyword":"Scenario","steps":[{"result":{"duration":992600,"status":"passed"},"line":5,"name":"user open website","match":{"location":"com.automation.steps.StepDefinition.user_open_website()"},"keyword":"Given "},{"result":{"duration":996700,"status":"passed"},"line":6,"name":"verify user is on login page","match":{"location":"com.automation.steps.StepDefinition.verify_user_is_on_login_page()"},"keyword":"Then "},{"result":{"duration":998000,"status":"passed"},"line":7,"name":"user login with username \"admin\" and password \"admin123\"","match":{"arguments":[{"val":"\"admin\"","offset":25},{"val":"\"admin123\"","offset":46}],"location":"com.automation.steps.StepDefinition.user_login_with_username_and_password(java.lang.String,java.lang.String)"},"keyword":"When "},{"result":{"status":"passed"},"line":8,"name":"verify user is on homepage","match":{"location":"com.automation.steps.StepDefinition.verify_user_is_on_homepage()"},"keyword":"Then "},{"result":{"duration":2990900,"status":"passed"},"line":9,"name":"user click on add to cart button of first item","match":{"location":"com.automation.steps.StepDefinition.user_click_on_add_to_cart_button_of_first_item()"},"keyword":"When "},{"result":{"status":"passed"},"line":10,"name":"verify cart icon display qantity of item","match":{"location":"com.automation.steps.StepDefinition.verify_cart_icon_display_qantity_of_item()"},"keyword":"Then "},{"result":{"status":"passed"},"line":11,"name":"user click on cart icon","match":{"location":"com.automation.steps.StepDefinition.user_click_on_cart_icon()"},"keyword":"When "},{"result":{"status":"passed"},"line":12,"name":"verify user is on cart page","match":{"location":"com.automation.steps.StepDefinition.verify_user_is_on_cart_page()"},"keyword":"Then "},{"result":{"status":"passed"},"line":13,"name":"user click on remove button","match":{"location":"com.automation.steps.StepDefinition.user_click_on_remove_button()"},"keyword":"When "},{"result":{"duration":1367300,"status":"passed"},"line":14,"name":"verify cart page is empty","match":{"location":"com.automation.steps.StepDefinition.verify_cart_page_is_empty()"},"keyword":"Then "}],"tags":[{"name":"@Regression"},{"name":"@Priya"}]}],"name":"To Verify Cart Page Functionalities","description":"","id":"to-verify-cart-page-functionalities","keyword":"Feature","uri":"file:src/test/resources/features/CartPageTest.feature","tags":[]},{"line":1,"elements":[{"line":5,"name":"","description":"","type":"background","keyword":"Background","steps":[{"result":{"duration":992600,"status":"passed"},"line":6,"name":"user open website","match":{"location":"com.automation.steps.StepDefinition.user_open_website()"},"keyword":"Given "},{"result":{"status":"passed"},"line":7,"name":"verify user is on login page","match":{"location":"com.automation.steps.StepDefinition.verify_user_is_on_login_page()"},"keyword":"Then "}]},{"start_timestamp":"2023-02-01T14:02:00.353Z","before":[{"result":{"duration":1995500,"status":"passed"},"match":{"location":"com.automation.steps.Hooks.setUp()"}}],"line":10,"name":"Verify user can login with valid credentials","description":"","id":"validate-login-functionalities;verify-user-can-login-with-valid-credentials","after":[{"result":{"duration":997600,"status":"passed"},"match":{"location":"com.automation.steps.Hooks.cleanUp()"}}],"type":"scenario","keyword":"Scenario","steps":[{"result":{"duration":998000,"status":"passed"},"line":11,"name":"user login with username \"admin\" and password \"admin123\"","match":{"arguments":[{"val":"\"admin\"","offset":25},{"val":"\"admin123\"","offset":46}],"location":"com.automation.steps.StepDefinition.user_login_with_username_and_password(java.lang.String,java.lang.String)"},"keyword":"When "},{"result":{"status":"passed"},"line":12,"name":"verify user is on homepage","match":{"location":"com.automation.steps.StepDefinition.verify_user_is_on_homepage()"},"keyword":"Then "}],"tags":[{"name":"@Smoke"},{"name":"@Chirag"}]},{"line":5,"name":"","description":"","type":"background","keyword":"Background","steps":[{"result":{"status":"passed"},"line":6,"name":"user open website","match":{"location":"com.automation.steps.StepDefinition.user_open_website()"},"keyword":"Given "},{"result":{"status":"passed"},"line":7,"name":"verify user is on login page","match":{"location":"com.automation.steps.StepDefinition.verify_user_is_on_login_page()"},"keyword":"Then "}]},{"start_timestamp":"2023-02-01T14:02:00.409Z","before":[{"result":{"status":"passed"},"match":{"location":"com.automation.steps.Hooks.setUp()"}}],"line":21,"name":"Verify user cannot login with invalid credentials","description":"","id":"validate-login-functionalities;verify-user-cannot-login-with-invalid-credentials;;2","after":[{"result":{"duration":997000,"status":"passed"},"match":{"location":"com.automation.steps.Hooks.cleanUp()"}}],"type":"scenario","keyword":"Scenario Outline","steps":[{"result":{"status":"passed"},"line":16,"name":"user login with username \"wronguser\" and password \"wrongpass\"","match":{"arguments":[{"val":"\"wronguser\"","offset":25},{"val":"\"wrongpass\"","offset":50}],"location":"com.automation.steps.StepDefinition.user_login_with_username_and_password(java.lang.String,java.lang.String)"},"keyword":"When "},{"result":{"status":"passed"},"line":17,"name":"verify invalid login error message is displayed","match":{"location":"com.automation.steps.StepDefinition.verify_invalid_login_error_message_is_displayed()"},"keyword":"Then "}],"tags":[{"name":"@Regression"},{"name":"@Krina"}]},{"line":5,"name":"","description":"","type":"background","keyword":"Background","steps":[{"result":{"status":"passed"},"line":6,"name":"user open website","match":{"location":"com.automation.steps.StepDefinition.user_open_website()"},"keyword":"Given "},{"result":{"duration":1003400,"status":"passed"},"line":7,"name":"verify user is on login page","match":{"location":"com.automation.steps.StepDefinition.verify_user_is_on_login_page()"},"keyword":"Then "}]},{"start_timestamp":"2023-02-01T14:02:00.424Z","before":[{"result":{"duration":1998200,"status":"passed"},"match":{"location":"com.automation.steps.Hooks.setUp()"}}],"line":22,"name":"Verify user cannot login with invalid credentials","description":"","id":"validate-login-functionalities;verify-user-cannot-login-with-invalid-credentials;;3","after":[{"result":{"status":"passed"},"match":{"location":"com.automation.steps.Hooks.cleanUp()"}}],"type":"scenario","keyword":"Scenario Outline","steps":[{"result":{"duration":4975900,"status":"passed"},"line":16,"name":"user login with username \"ADMIN\" and password \"admin123\"","match":{"arguments":[{"val":"\"ADMIN\"","offset":25},{"val":"\"admin123\"","offset":46}],"location":"com.automation.steps.StepDefinition.user_login_with_username_and_password(java.lang.String,java.lang.String)"},"keyword":"When "},{"result":{"duration":996100,"status":"passed"},"line":17,"name":"verify invalid login error message is displayed","match":{"location":"com.automation.steps.StepDefinition.verify_invalid_login_error_message_is_displayed()"},"keyword":"Then "}],"tags":[{"name":"@Regression"},{"name":"@Krina"}]},{"line":5,"name":"","description":"","type":"background","keyword":"Background","steps":[{"result":{"status":"passed"},"line":6,"name":"user open website","match":{"location":"com.automation.steps.StepDefinition.user_open_website()"},"keyword":"Given "},{"result":{"status":"passed"},"line":7,"name":"verify user is on login page","match":{"location":"com.automation.steps.StepDefinition.verify_user_is_on_login_page()"},"keyword":"Then "}]},{"start_timestamp":"2023-02-01T14:02:00.451Z","before":[{"result":{"duration":993300,"status":"passed"},"match":{"location":"com.automation.steps.Hooks.setUp()"}}],"line":23,"name":"Verify user cannot login with invalid credentials","description":"","id":"validate-login-functionalities;verify-user-cannot-login-with-invalid-credentials;;4","after":[{"result":{"status":"passed"},"match":{"location":"com.automation.steps.Hooks.cleanUp()"}}],"type":"scenario","keyword":"Scenario Outline","steps":[{"result":{"status":"passed"},"line":16,"name":"user login with username \"\" and password \"\"","match":{"arguments":[{"val":"\"\"","offset":25},{"val":"\"\"","offset":41}],"location":"com.automation.steps.StepDefinition.user_login_with_username_and_password(java.lang.String,java.lang.String)"},"keyword":"When "},{"result":{"status":"passed"},"line":17,"name":"verify invalid login error message is displayed","match":{"location":"com.automation.steps.StepDefinition.verify_invalid_login_error_message_is_displayed()"},"keyword":"Then "}],"tags":[{"name":"@Regression"},{"name":"@Krina"}]},{"line":5,"name":"","description":"","type":"background","keyword":"Background","steps":[{"result":{"duration":997300,"status":"passed"},"line":6,"name":"user open website","match":{"location":"com.automation.steps.StepDefinition.user_open_website()"},"keyword":"Given "},{"result":{"status":"passed"},"line":7,"name":"verify user is on login page","match":{"location":"com.automation.steps.StepDefinition.verify_user_is_on_login_page()"},"keyword":"Then "}]},{"start_timestamp":"2023-02-01T14:02:00.460Z","before":[{"result":{"status":"passed"},"match":{"location":"com.automation.steps.Hooks.setUp()"}}],"line":24,"name":"Verify user cannot login with invalid credentials","description":"","id":"validate-login-functionalities;verify-user-cannot-login-with-invalid-credentials;;5","after":[{"result":{"duration":997700,"status":"passed"},"match":{"location":"com.automation.steps.Hooks.cleanUp()"}}],"type":"scenario","keyword":"Scenario Outline","steps":[{"result":{"status":"passed"},"line":16,"name":"user login with username \"admin\" and password \"admin\"","match":{"arguments":[{"val":"\"admin\"","offset":25},{"val":"\"admin\"","offset":46}],"location":"com.automation.steps.StepDefinition.user_login_with_username_and_password(java.lang.String,java.lang.String)"},"keyword":"When "},{"result":{"status":"passed"},"line":17,"name":"verify invalid login error message is displayed","match":{"location":"com.automation.steps.StepDefinition.verify_invalid_login_error_message_is_displayed()"},"keyword":"Then "}],"tags":[{"name":"@Regression"},{"name":"@Krina"}]}],"name":"Validate Login Functionalities","description":"  Developer - Krina\n  Tester - Priya","id":"validate-login-functionalities","keyword":"Feature","uri":"file:src/test/resources/features/Login.feature","tags":[]},{"line":1,"elements":[{"start_timestamp":"2023-02-01T14:02:00.354Z","before":[{"result":{"duration":1995500,"status":"passed"},"match":{"location":"com.automation.steps.Hooks.setUp()"}}],"line":6,"name":"Verify user can Logout from the application","description":"","id":"validate-logout-functionalities;verify-user-can-logout-from-the-application","after":[{"result":{"status":"passed"},"match":{"location":"com.automation.steps.Hooks.cleanUp()"}}],"type":"scenario","keyword":"Scenario","steps":[{"result":{"duration":992600,"status":"passed"},"line":7,"name":"user open website","match":{"location":"com.automation.steps.StepDefinition.user_open_website()"},"keyword":"Given "},{"result":{"status":"passed"},"line":8,"name":"verify user is on login page","match":{"location":"com.automation.steps.StepDefinition.verify_user_is_on_login_page()"},"keyword":"Then "},{"result":{"duration":998000,"status":"passed"},"line":9,"name":"user login with username \"admin\" and password \"admin123\"","match":{"arguments":[{"val":"\"admin\"","offset":25},{"val":"\"admin123\"","offset":46}],"location":"com.automation.steps.StepDefinition.user_login_with_username_and_password(java.lang.String,java.lang.String)"},"keyword":"When "},{"result":{"duration":997300,"status":"passed"},"line":10,"name":"verify user is on homepage","match":{"location":"com.automation.steps.StepDefinition.verify_user_is_on_homepage()"},"keyword":"Then "},{"result":{"status":"passed"},"line":11,"name":"user click on burger icon","match":{"location":"com.automation.steps.StepDefinition.user_click_on_burger_icon()"},"keyword":"When "},{"result":{"status":"passed"},"line":12,"name":"click on logout button","match":{"location":"com.automation.steps.StepDefinition.click_on_logout_button()"},"keyword":"And "},{"result":{"status":"passed"},"line":13,"name":"verify user is on login page","match":{"location":"com.automation.steps.StepDefinition.verify_user_is_on_login_page()"},"keyword":"Then "}],"tags":[{"name":"@Smoke"}]}],"name":"Validate Logout Functionalities","description":"  Developer - Krina\n  Tester - HariKrishna","id":"validate-logout-functionalities","keyword":"Feature","uri":"file:src/test/resources/features/Logout.feature","tags":[]}]